relentless/__init__.py
relentless/collections.py
relentless/data.py
relentless/math.py
relentless/mpi.py
relentless/model/__init__.py
relentless/model/ensemble.py
relentless/model/extent.py
relentless/model/variable.py
relentless/model/potential/__init__.py
relentless/model/potential/pair.py
relentless/model/potential/potential.py
relentless/optimize/__init__.py
relentless/optimize/criteria.py
relentless/optimize/method.py
relentless/optimize/objective.py
relentless/simulate/__init__.py
relentless/simulate/analyze.py
relentless/simulate/dilute.py
relentless/simulate/hoomd.py
relentless/simulate/initialize.py
relentless/simulate/lammps.py
relentless/simulate/md.py
relentless/simulate/simulate.py
relentless-0.2.1.dist-info/LICENSE
relentless-0.2.1.dist-info/METADATA
relentless-0.2.1.dist-info/WHEEL
relentless-0.2.1.dist-info/top_level.txt
relentless-0.2.1.dist-info/RECORD
