Metadata-Version: 2.1
Name: relentless
Version: 0.2.1
Summary: Computational materials design, with less code
Home-page: https://github.com/mphowardlab/relentless
Author: Michael P. Howard
Author-email: mphoward@auburn.edu
Project-URL: Documentation, https://relentless.readthedocs.io
Project-URL: Source Code, https://github.com/mphowardlab/relentless
Project-URL: Issue Tracker, https://github.com/mphowardlab/relentless/issues
Classifier: Intended Audience :: Science/Research
Classifier: License :: OSI Approved :: BSD License
Classifier: Topic :: Scientific/Engineering :: Chemistry
Classifier: Topic :: Scientific/Engineering :: Physics
Classifier: Programming Language :: Python :: 3.8
Classifier: Programming Language :: Python :: 3.9
Classifier: Programming Language :: Python :: 3.10
Classifier: Programming Language :: Python :: 3.11
Classifier: Programming Language :: Python :: 3.12
Requires-Python: >=3.8
License-File: LICENSE
Requires-Dist: freud-analysis>=2
Requires-Dist: lammpsio>=0.6.1
Requires-Dist: networkx>=2.5
Requires-Dist: numpy
Requires-Dist: packaging
Requires-Dist: scipy
Requires-Dist: gsd<3.3.0; python_version < "3.9"
Requires-Dist: gsd; python_version >= "3.9"
